MongodbManual/README.md
MongodbManual/__init__.py
MongodbManual/__main__.py
MongodbManual/file.epub
MongodbManual/index.html
MongodbManual/css/__init__.py
MongodbManual/css/annotations.css
MongodbManual/css/main.css
MongodbManual/css/normalize.css
MongodbManual/css/popup.css
MongodbManual/font/__init__.py
MongodbManual/font/fontello.eot
MongodbManual/font/fontello.svg
MongodbManual/font/fontello.ttf
MongodbManual/font/fontello.woff
MongodbManual/img/__init__.py
MongodbManual/img/annotator-glyph-sprite.png
MongodbManual/img/annotator-icon-sprite.png
MongodbManual/img/apple-touch-icon.png
MongodbManual/img/cancelfullscreen.png
MongodbManual/img/close.png
MongodbManual/img/fullscreen.png
MongodbManual/img/loader.gif
MongodbManual/img/menu-icon.png
MongodbManual/img/save.png
MongodbManual/img/saved.png
MongodbManual/img/settings-s.png
MongodbManual/img/settings.png
MongodbManual/img/star.png
MongodbManual/js/__init__.py
MongodbManual/js/epub.js
MongodbManual/js/epub.min.js
MongodbManual/js/epub.min.map
MongodbManual/js/hooks.min.js
MongodbManual/js/hooks.min.map
MongodbManual/js/reader.js
MongodbManual/js/reader.js.map
MongodbManual/js/reader.min.js
MongodbManual/js/reader.min.map
MongodbManual/js/hooks/__init__.py
MongodbManual/js/hooks/extensions/__init__.py
MongodbManual/js/hooks/extensions/highlight.js
MongodbManual/js/libs/__init__.py
MongodbManual/js/libs/jquery.min.js
MongodbManual/js/libs/localforage.min.js
MongodbManual/js/libs/screenfull.js
MongodbManual/js/libs/screenfull.min.js
MongodbManual/js/libs/zip.min.js
MongodbManual/js/plugins/__init__.py
MongodbManual/js/plugins/hypothesis.js
MongodbManual/js/plugins/search.js
mongodb_manual-2024.3.2.0.dist-info/METADATA
mongodb_manual-2024.3.2.0.dist-info/WHEEL
mongodb_manual-2024.3.2.0.dist-info/entry_points.txt
mongodb_manual-2024.3.2.0.dist-info/top_level.txt
mongodb_manual-2024.3.2.0.dist-info/RECORD
